{"name": "imaginative", "trans": [{"dict": "2024HongBao T2", "values": ["富有想象力的，爱想象的"]}, {"dict": "English_II", "values": ["a.富于想像力的，爱想像的"]}, {"dict": "PTE_Basic_apeuni", "values": ["adj. 富于想象的；有创造力的"]}, {"dict": "PTE_junior", "values": ["adj. 富于想像力的; 运用想像力的\n\n副 词:  \nimaginatively"]}, {"dict": "TOEFL_ZhangHongYan", "values": ["adj. 富于想象力的，创新的；运用想象（力）的，虚构的"]}, {"dict": "TOEIC", "values": ["adj. 富于想像力的; 运用想像力的副 词:imaginatively"]}, {"dict": "cet6", "values": ["富有想象力的， 爱想象的 (adj.)"]}, {"dict": "coca_20000", "values": ["adj.富于想像力的，运用想像力的,想象或创造出来的,沉溺于想象的,虚假的"]}, {"dict": "ielts", "values": ["富有想象力的； 创新的"]}, {"dict": "ielts-real-3", "values": ["adj. 富于想像力的; 运用想像力的副 词: imaginatively"]}, {"dict": "ielts_disorder", "values": ["adj.想象的, 虚构的。"]}, {"dict": "ielts_order", "values": ["adj.想象的, 虚构的。"]}, {"dict": "kaoyan", "values": ["富有想象力的； 爱想象的"]}, {"dict": "kaoyan_2024", "values": ["adj.富于想象的；有创造力的"]}, {"dict": "level4", "values": ["富于想象的；有创造力的"]}, {"dict": "level8", "values": ["富于想象的；有创造力的"]}, {"dict": "sat", "values": ["富有想象力的， 想象的； 幻想的， 虚构的"]}, {"dict": "self-study_English3", "values": ["adj. 富于想象的；有创造力的"]}, {"dict": "toefl", "values": ["富有想象力的； 创新的"]}, {"dict": "xinghuoqiaoji_4", "values": ["adj. 富于想象的；有创造力的"]}], "usphone": "ɪˈmædʒɪnətɪv", "ukphone": "ɪˈmædʒɪnətɪv"}