{"name": "inalienable", "trans": [{"dict": "ZaiYaoNiMing_GRE3000", "values": ["adj. 不可剥夺的，不能让与的"]}, {"dict": "gmat", "values": ["不可让与的， 不可剥夺的"]}, {"dict": "gre", "values": ["不能转让的； 不可剥夺的"]}, {"dict": "gre3000", "values": ["不可剥夺的，不能让与的"]}, {"dict": "ielts", "values": ["不可剥夺的， 不可分割的"]}, {"dict": "ielts_disorder", "values": ["adj.(指权利等)不能让与的, 不能剥夺的。"]}, {"dict": "ielts_order", "values": ["adj.(指权利等)不能让与的, 不能剥夺的。"]}, {"dict": "sat", "values": ["不能让与的， 不可剥夺的"]}], "usphone": "ɪn'elɪənəbl", "ukphone": "ɪn'eɪliənəbl"}