{"name": "indicate", "trans": [{"dict": "2024HongBao T1", "values": ["指出，指示；迹象，暗示"]}, {"dict": "4000_Essential_English_Words1", "values": ["When we indicate something, we show or point out our thoughts or plans."]}, {"dict": "4000_Essential_English_Words2", "values": ["They indicated that things would be likely to improve soon."]}, {"dict": "English_II", "values": ["vt.指示，指出；表示，表明"]}, {"dict": "Oxford3000", "values": ["指出，指示；迹象，暗示"]}, {"dict": "Oxford5000", "values": ["vt. 标示，指示，指出象征；表明或暗示…的可能性", "时态:indicated，indicating，indicates形容词:indicatory"]}, {"dict": "Oxford5000", "values": ["vt. 标示，指示，指出象征；表明或暗示…的可能性", "时态:indicated，indicating，indicates形容词:indicatory"]}, {"dict": "PTE_Advanced_apeuni.json", "values": ["vt. 表明；指出；预示；象征"]}, {"dict": "PTE_Basic_apeuni", "values": ["vt. 表明；指出；预示；象征"]}, {"dict": "PTE_FIB_L", "values": ["- vt. 标示，指示，指出\n- 象征；表明或暗示…的可能性\n\n时 态:  \nindicated，indicating，indicates \n\n形容词:  \nindicatory"]}, {"dict": "PTE_FIB_R_junior", "values": ["- vt. 标示，指示，指出\n- 象征；表明或暗示…的可能性\n\n时 态:  \nindicated，indicating，indicates \n\n形容词:  \nindicatory"]}, {"dict": "PTE_WFD", "values": ["- vt. 标示，指示，指出\n- 象征；表明或暗示…的可能性\n\n时 态:  \nindicated，indicating，indicates \n\n形容词:  \nindicatory"]}, {"dict": "PTE_junior", "values": ["- vt. 标示，指示，指出\n- 象征；表明或暗示…的可能性\n\n时 态:  \nindicated，indicating，indicates \n\n形容词:  \nindicatory"]}, {"dict": "PTE_senior", "values": ["- vt. 标示，指示，指出\n- 象征；表明或暗示…的可能性\n\n时 态:  \nindicated，indicating，indicates \n\n形容词:  \nindicatory"]}, {"dict": "TOEFL_ZhangHongYan", "values": ["v. 表明，标示；象征，暗示；间接提及，示意；指示，指出；&lt;英&gt;（用灯光或手臂）打行车转向信号；有必要，被建议"]}, {"dict": "TOEIC", "values": ["vt. 标示，指示，指出象征；表明或暗示…的可能性", "时态:indicated，indicating，indicates形容词:indicatory"]}, {"dict": "adult self-study examination", "values": ["v.表明"]}, {"dict": "bec2", "values": ["表明；指出；预示；象征"]}, {"dict": "bec3", "values": ["标示， 指示， 指出； 表明， 暗示"]}, {"dict": "cet4", "values": ["标示， 表示， 表明"]}, {"dict": "cet4-sub", "values": ["vt. 表明；指出；预示；象征"]}, {"dict": "coca_20000", "values": ["vt.表明，标示，指示,象征，暗示，预示,医显示需要做…的治疗"]}, {"dict": "dancimimi_1", "values": ["vt. 表明；指出；预示；象征"]}, {"dict": "dancimimi_1", "values": ["vt. 表明；指出；预示；象征"]}, {"dict": "dancimimi_2", "values": ["vt. 表明；指出；预示；象征"]}, {"dict": "dancimimi_2", "values": ["vt. 表明；指出；预示；象征"]}, {"dict": "gmat", "values": ["显示， 表明； 指出"]}, {"dict": "gre", "values": ["指示， 指出； 象征， 显示"]}, {"dict": "ielts", "values": ["标示， 表示， 表明； 象征； 暗示， 示意"]}, {"dict": "ielts_disorder", "values": ["v. 指出，指示；表明，暗示"]}, {"dict": "ielts_order", "values": ["v. 指出，指示；表明，暗示"]}, {"dict": "itVocabulary", "values": ["vt.指示，表示"]}, {"dict": "kaoyan", "values": ["指出； 指示 A；表明或暗示…的可能性 A"]}, {"dict": "kaoyan_2024", "values": ["vt. 表明；指出；预示；象征"]}, {"dict": "kaoyanshanguo_2023", "values": ["v. 表明vt. 暗示；指出"]}, {"dict": "level4", "values": ["表明；指出；预示；象征"]}, {"dict": "level8", "values": ["表明；指出；预示；象征"]}, {"dict": "longman_communication_3000_words", "values": ["表明, 指示, 注明, 显示 (verb.)"]}, {"dict": "pets3", "values": ["v.指出，指示；表明，暗示"]}, {"dict": "pets3-2023", "values": ["vt.标示，表示，指明，表明，v.显示，象征，指示"]}, {"dict": "self-study_English3", "values": ["vt. 表明；指出；预示；象征"]}, {"dict": "self-study_English3", "values": ["vt. 表明；指出；预示；象征"]}, {"dict": "toefl", "values": ["表明， 显示； 指出， 指示； 象征， 预示； 暗示， 间接提及"]}, {"dict": "top_1000_verb_Words", "values": ["To indicate is to show or suggest something, often through gestures or signs."]}, {"dict": "top_2000_English_Words", "values": ["verb"]}, {"dict": "xinghuoqiaoji_4", "values": ["vt. 表明；指出；预示；象征"]}, {"dict": "xinghuoqiaoji_6", "values": ["vt. 表明；指出；预示；象征"]}, {"dict": "xinghuoqiaoji_6", "values": ["vt. 表明；指出；预示；象征"]}], "usphone": "ˈɪndɪkeɪt", "ukphone": "ˈɪndɪkeɪt"}