{"name": "dimensional", "trans": [{"dict": "cet6-sub", "values": ["adj. 空间的；尺寸的"]}, {"dict": "coca_20000", "values": ["adj.尺寸的,<物>量纲的,<数>因次的,维的"]}, {"dict": "ielts", "values": ["…度空间的， …维的"]}, {"dict": "ielts_disorder", "values": ["adj.尺寸的"]}, {"dict": "ielts_order", "values": ["adj.尺寸的"]}, {"dict": "itVocabulary", "values": ["n.尺寸的，…维的"]}, {"dict": "kaoyan_2024", "values": ["adj.空间的；尺寸的"]}, {"dict": "level8", "values": ["空间的；尺寸的"]}, {"dict": "toefl", "values": ["…度空间的"]}, {"dict": "xinghuoqiaoji_4", "values": ["adj. 空间的；尺寸的"]}], "usphone": "dɪˈmenʃənl,daɪˈmenʃənl", "ukphone": "dɪˈmenʃənl,daɪˈmenʃənl"}