{"name": "disarm", "trans": [{"dict": "PTE_FIB_R_senior", "values": ["- vi. 裁军\n- vt. 使息怒\n\n时 态:  \ndisarmed, disarming, disarms \n\n名 词:  \ndisarmer"]}, {"dict": "SATen", "values": ["to take away the weapons of, to render defenceless"]}, {"dict": "TOEFL_ZhangHongYan", "values": ["v. 缴……的械，解除……的武装；拆除（炸弹等的）引信；使友好，消除……的敌意；裁减军备，裁军 n. 解除（某人的）武器"]}, {"dict": "ZaiYaoNiMing_GRE3000", "values": ["vt. 使息怒，平息，抚慰"]}, {"dict": "coca_20000", "values": ["vi.裁军,解除武装,放下武器vt.使缴械,使息怒,解除武装,缓和"]}, {"dict": "gre", "values": ["使缴械； 使缓和"]}, {"dict": "gre3000", "values": ["使息怒，平息，抚慰"]}, {"dict": "ielts_disorder", "values": ["vt.解除武装, 回复平常的编制, 缓和, 消除(敌意,疑虑)。vi.放下武器"]}, {"dict": "ielts_order", "values": ["vt.解除武装, 回复平常的编制, 缓和, 消除(敌意,疑虑)。vi.放下武器"]}, {"dict": "level8", "values": ["解除武装；裁军；缓和"]}, {"dict": "toefl", "values": ["解除武装； 裁军； 消除， 消解"]}, {"dict": "voa", "values": ["放下武器"]}, {"dict": "xinghuoqiaoji_6", "values": ["vt. 解除武装；裁军；缓和,vi. 放下武器；裁减军备"]}], "usphone": "dɪˈsɑrm", "ukphone": "dɪsˈɑːm"}