{"name": "dismay", "trans": [{"dict": "TOEFL_ZhangHongYan", "values": ["n. 担忧；失望，沮丧；惊愕 v. 使担忧；使失望，使沮丧；使惊恐"]}, {"dict": "ZaiYaoNiMing_GRE3000", "values": ["vt. 使失去勇气", "vt. 使不安，使焦虑"]}, {"dict": "cet6", "values": ["失望，气馁；惊恐 (n.)", "使失望， 使气馁； 使惊恐 (vt.)"]}, {"dict": "coca_20000", "values": ["vt.使惊愕，使焦虑，使气馁n.惊愕，气馁"]}, {"dict": "coca_20000", "values": ["vt.使惊愕，使焦虑，使气馁n.惊愕，气馁"]}, {"dict": "gmat", "values": ["沮丧"]}, {"dict": "gre", "values": ["使气馁", "沮丧，气馁"]}, {"dict": "gre3000", "values": ["使失去勇气；使不安，使焦虑"]}, {"dict": "ielts_disorder", "values": ["n./vt. (使)灰心丧气;惊愕"]}, {"dict": "ielts_order", "values": ["n./vt. (使)灰心丧气;惊愕"]}, {"dict": "kaoyan", "values": ["惊恐， 惊愕；失望， 绝望", "使惊恐， 使惊愕；失望， 绝望"]}, {"dict": "level4", "values": ["沮丧，灰心；惊慌", "使沮丧；使惊慌"]}, {"dict": "level8", "values": ["沮丧，灰心；惊慌", "使沮丧；使惊慌"]}, {"dict": "toefl", "values": ["使气馁，使沮丧；使诧异", "灰心， 气馁； 诧异"]}, {"dict": "xinghuoqiaoji_6", "values": ["n. 沮丧，灰心；惊慌,vt. 使沮丧；使惊慌"]}], "usphone": "dɪs'meɪ", "ukphone": "dɪs'meɪ"}