{"name": "applicant", "trans": [{"dict": "4000_Essential_English_Words1", "values": ["An applicant is someone who writes a request to be considered for a job or prize."]}, {"dict": "4000_Essential_English_Words2", "values": ["Lots of applicants came into the store when the job position became available."]}, {"dict": "English_II", "values": ["n.申请人，请求者"]}, {"dict": "IELTS-807", "values": ["n.申请人"]}, {"dict": "IELTS_tinglichangjing", "values": ["申请人"]}, {"dict": "Oxford5000", "values": ["n. 申请人, 求职人"]}, {"dict": "Oxford5000", "values": ["n. 申请人, 求职人"]}, {"dict": "PTE_Advanced_apeuni.json", "values": ["n. 申请人，申请者；请求者"]}, {"dict": "PTE_Basic_apeuni", "values": ["n. 申请人，申请者；请求者"]}, {"dict": "PTE_WFD", "values": ["n. 申请人, 求职人"]}, {"dict": "PTE_junior", "values": ["n. 申请人, 求职人"]}, {"dict": "PTE_senior", "values": ["n. 申请人, 求职人"]}, {"dict": "TOEIC", "values": ["n. 申请人, 求职人"]}, {"dict": "bec2", "values": ["申请人，申请者；请求者"]}, {"dict": "bec3", "values": ["申请人， 候补人"]}, {"dict": "cet4", "values": ["申请人"]}, {"dict": "cet4-sub", "values": ["n. 申请人，申请者；请求者"]}, {"dict": "coca_20000", "values": ["n.申请人，求职人,请求者"]}, {"dict": "dancimimi_1", "values": ["n. 申请人，申请者；请求者"]}, {"dict": "dancimimi_1", "values": ["n. 申请人，申请者；请求者"]}, {"dict": "dancimimi_2", "values": ["n. 申请人，申请者；请求者"]}, {"dict": "gre", "values": ["申请人"]}, {"dict": "ielts", "values": ["申请人"]}, {"dict": "ielts-real-high", "values": ["n. 申请人, 求职人"]}, {"dict": "ieltsWang5", "values": ["申请人"]}, {"dict": "ielts_disorder", "values": ["n. 申请人,请求者"]}, {"dict": "ielts_order", "values": ["n. 申请人,请求者"]}, {"dict": "kaoyan_2024", "values": ["n.申请人，申请者；请求者"]}, {"dict": "level4", "values": ["申请人，申请者；请求者"]}, {"dict": "level8", "values": ["申请人，申请者；请求者"]}, {"dict": "self-study_English3", "values": ["n. 申请人，申请者；请求者"]}, {"dict": "toefl", "values": ["申请者"]}, {"dict": "xinghuoqiaoji_4", "values": ["n. 申请人，申请者；请求者"]}], "usphone": "'æplɪkənt", "ukphone": "'æplɪkənt"}