{"name": "assistant", "trans": [{"dict": "2024HongBao T2", "values": ["助手，助教"]}, {"dict": "IELTS-807", "values": ["助手"]}, {"dict": "IELTSVocabularyBible", "values": ["n. 助手，助理，助教 adj. 辅助的，助理的；有帮助的"]}, {"dict": "Oxford3000", "values": ["助手，助教"]}, {"dict": "Oxford5000", "values": ["n. 助手，副手，助理；助教"]}, {"dict": "Oxford5000", "values": ["n. 助手，副手，助理；助教"]}, {"dict": "PTE_Advanced_apeuni.json", "values": ["n. 助手，助理，助教"]}, {"dict": "PTE_Basic_apeuni", "values": ["n. 助手，助理，助教"]}, {"dict": "PTE_WFD", "values": ["n. 助手，副手，助理；助教"]}, {"dict": "PTE_junior", "values": ["n. 助手，副手，助理；助教"]}, {"dict": "PTE_senior", "values": ["n. 助手，副手，助理；助教"]}, {"dict": "adult self-study examination", "values": ["n.助手"]}, {"dict": "bec2", "values": ["助手，助理，助教", "辅助的，助理的；有帮助的"]}, {"dict": "bec3", "values": ["帮助的，辅助的", "助手， 助教； 辅助物"]}, {"dict": "cet4", "values": ["助理的， 辅助的", "助手，助理，助教"]}, {"dict": "cet4-sub", "values": ["n. 助手，助理，助教", "adj. 辅助的，助理的；有帮助的"]}, {"dict": "coca_20000", "values": ["n.助手，助理,化学（染色的）助剂,辅助物,店员，伙计adj.助理的,辅助的,有帮助的,副的"]}, {"dict": "coca_20000", "values": ["n.助手，助理,化学（染色的）助剂,辅助物,店员，伙计adj.助理的,辅助的,有帮助的,副的"]}, {"dict": "dancimimi_1", "values": ["n. 助手，助理，助教", "adj. 辅助的，助理的；有帮助的"]}, {"dict": "dancimimi_2", "values": ["n. 助手，助理，助教", "adj. 辅助的，助理的；有帮助的"]}, {"dict": "heqiong", "values": ["助手"]}, {"dict": "ielts", "values": ["助理的；"]}, {"dict": "ieltsWang5", "values": ["助手"]}, {"dict": "ielts_disorder", "values": ["a. 帮助的，辅助的n. 助手，助教；辅助物"]}, {"dict": "ielts_order", "values": ["a. 帮助的，辅助的n. 助手，助教；辅助物"]}, {"dict": "kaoyan_2024", "values": ["n.助手，助理，助教adj.辅助的，助理的；有帮助的"]}, {"dict": "level8", "values": ["助手，助理，助教", "辅助的，助理的；有帮助的"]}, {"dict": "longman_communication_3000_words", "values": ["助理, 助手, 辅助, 副 (noun.)"]}, {"dict": "pets3", "values": ["n.助理，助手"]}, {"dict": "pets3-2023", "values": ["n.助手，助理，助教，adj.副的"]}, {"dict": "self-study_English2", "values": ["n. 助手，助理，助教"]}, {"dict": "toefl", "values": ["辅助的，助理的；副的", "助手， 助教"]}, {"dict": "top_1500_nouns_Words", "values": ["An assistant is a person who helps or supports someone in their work or duties."]}, {"dict": "xinghuoqiaoji_4", "values": ["n. 助手，助理，助教,adj. 辅助的，助理的；有帮助的"]}], "usphone": "əˈsɪstənt", "ukphone": "əˈsɪstənt"}