{"name": "exempt", "trans": [{"dict": "PTE_WFD", "values": ["- vt. 免除；豁免\n- adj. 被免除的；被豁免的\n- n. 免税者；被免除义务者\n\n\n时 态:  \nexempted, exempting, exempts \n\n形容词:  \nexemptible"]}, {"dict": "SATen", "values": ["to grant (someone) freedom or immunity from"]}, {"dict": "TOEFL_ZhangHongYan", "values": ["adj. 被免除……的，获豁免的 v. 免除，豁免 n. 被免除（义务或责任）的人（尤指被免税者）"]}, {"dict": "TOEIC", "values": ["vt. 免除；豁免", "adj. 被免除的；被豁免的", "n. 免税者；被免除义务者", "时态:exempted, exempting, exempts形容词:exemptible"]}, {"dict": "ZaiYaoNiMing_GRE3000", "values": ["vt.使免除"]}, {"dict": "bec2", "values": ["免除；豁免", "被免除的；被豁免的", "免税者；被免除义务者"]}, {"dict": "bec3", "values": ["被免除的， 被豁免的", "免除，豁免"]}, {"dict": "cet6", "values": ["被免除的， 被豁免的 (adj.)", "免除，豁免 (vt.)"]}, {"dict": "cet6-sub", "values": ["n. 免税者；被免除义务者", "adj. 被免除的；被豁免的", "vt. 免除；豁免"]}, {"dict": "coca_20000", "values": ["vt.使免除，豁免adj.被免除的，被豁免的n.被免除（义务，责任）的人,免税人"]}, {"dict": "coca_20000", "values": ["vt.使免除，豁免adj.被免除的，被豁免的n.被免除（义务，责任）的人,免税人"]}, {"dict": "dancimimi_1", "values": ["n. 免税者；被免除义务者", "adj. 被免除的；被豁免的", "vt. 免除；豁免"]}, {"dict": "dancimimi_2", "values": ["n. 免税者；被免除义务者", "adj. 被免除的；被豁免的", "vt. 免除；豁免"]}, {"dict": "gmat", "values": ["免除，豁免；", "被免除的"]}, {"dict": "gre", "values": ["被免除的，被豁免的", "免除， 豁免"]}, {"dict": "gre3000", "values": ["使免除"]}, {"dict": "ielts-real-2", "values": ["vt. 免除；豁免; adj. 被免除的；被豁免的; n. 免税者；被免除义务者 时 态: exempted, exempting, exempts 形容词: exemp..."]}, {"dict": "ielts_disorder", "values": ["vt./a. 免除,被豁免的"]}, {"dict": "ielts_order", "values": ["vt./a. 免除,被豁免的"]}, {"dict": "kaoyan", "values": ["被免除的， 被豁免的", "使…免除"]}, {"dict": "kaoyan_2024", "values": ["n.免税者；被免除义务者adj.被免除的；被豁免的vt.免除；豁免"]}, {"dict": "kaoyanshanguo_2023", "values": ["a. 免除（责任、付款等）vt. 免除"]}, {"dict": "sat", "values": ["被免除  的， 被豁免的", "免除，豁免"]}, {"dict": "toefl", "values": ["被免除的，被豁免的", "免除， 豁免"]}, {"dict": "xinghuoqiaoji_6", "values": ["n. 免税者；被免除义务者,adj. 被免除的；被豁免的,vt. 免除；豁免"]}], "usphone": "ɪɡˈzɛmpt", "ukphone": "ɪɡˈzɛmpt"}