{"name": "cabbage", "trans": [{"dict": "IELTSVocabularyBible", "values": ["n. 卷心菜，甘蓝菜，洋白菜；（俚)脑袋；（非正式、侮辱）植物人（常用于英式英语）；（俚）钱，尤指纸币（常用于美式俚语）"]}, {"dict": "PTE_Basic_apeuni", "values": ["n. 卷心菜，甘蓝菜，洋白菜；（俚)脑袋；（非正式、侮辱）植物人（常用于英式英语）；（俚）钱，尤指纸币（常用于美式俚语）"]}, {"dict": "PTE_junior", "values": ["n. 洋白菜, 卷心菜"]}, {"dict": "TOEFL_ZhangHongYan", "values": ["n. 卷心菜，洋白菜；（作蔬菜食用的）卷心菜叶子，洋白菜叶子；&lt;英，非正式&gt;（冒犯）（因受伤或疾病而）身心残损的人；&lt;英，非正式&gt;生活极乏味的人"]}, {"dict": "adult self-study examination", "values": ["n.卷心菜"]}, {"dict": "cet4", "values": ["洋白菜， 卷心菜"]}, {"dict": "coca_20000", "values": ["n.甘蓝（洋白菜、卷心菜）,<非正式、侮辱>植物人，常用于英式英语,<俚>钱，尤指纸币，常用于美式俚语,<俚>脑袋"]}, {"dict": "heqiong", "values": ["卷心菜"]}, {"dict": "ielts_disorder", "values": ["n. 洋白菜，卷心菜"]}, {"dict": "ielts_order", "values": ["n. 洋白菜，卷心菜"]}, {"dict": "kaoyan", "values": ["洋白菜， 卷心菜"]}, {"dict": "level8", "values": ["卷心菜，甘蓝菜，洋白菜；（俚)脑袋；（非正式、侮辱）植物人（常用于英式英语）；（俚）钱，尤指纸币（常用于美式俚语）"]}, {"dict": "pets3-2023", "values": ["n.洋白菜，卷心菜，vt.偷窃"]}, {"dict": "xinghuoqiaoji_6", "values": ["n. 卷心菜，甘蓝菜，洋白菜；（俚)脑袋；（非正式、侮辱）植物人（常用于英式英语）；（俚）钱，尤指纸币（常用于美式俚语）"]}], "usphone": "[ˈkæbɪdʒ]", "ukphone": "ˈkæbɪʤ"}