{"name": "nicely", "trans": [{"dict": "Oxford5000", "values": ["ad", "v. 很好地;令人满意地;令人愉快地;合宜地精确地;细微地(通常用于进行时)进展良好令人满意"]}, {"dict": "Oxford5000", "values": ["ad", "v. 很好地;令人满意地;令人愉快地;合宜地精确地;细微地(通常用于进行时)进展良好令人满意"]}, {"dict": "coca_20000", "values": ["adv.漂亮地,恰当地，规规矩矩地,精密地,非常讲究地adj.<口>健康的，强健的"]}, {"dict": "level8", "values": ["漂亮地；恰好地；精细地", "(Nicely)人名；(英)奈斯利"]}, {"dict": "longman_communication_3000_words", "values": ["好听, 好 (adv.)"]}, {"dict": "self-study_English2", "values": ["adv. 漂亮地；恰好地；精细地"]}], "usphone": "'naɪsli", "ukphone": "ˈnaɪslɪ"}