{"name": "noticeable", "trans": [{"dict": "Oxford5000", "values": ["adj. 显而易见的, 明显的, 显著的副 词:noticeably"]}, {"dict": "Oxford5000", "values": ["adj. 显而易见的, 明显的, 显著的副 词:noticeably"]}, {"dict": "PTE_Advanced_apeuni.json", "values": ["adj. 显而易见的，显著的；值得注意的"]}, {"dict": "PTE_Basic_apeuni", "values": ["adj. 显而易见的，显著的；值得注意的"]}, {"dict": "PTE_FIB_R_senior", "values": ["adj. 显而易见的, 明显的, 显著的\n\n副 词:  \nnoticeably"]}, {"dict": "PTE_Read_apeuni.json", "values": ["adj. 显而易见的，显著的；值得注意的"]}, {"dict": "PTE_junior", "values": ["adj. 显而易见的, 明显的, 显著的\n\n副 词:  \nnoticeably"]}, {"dict": "PTE_senior", "values": ["adj. 显而易见的, 明显的, 显著的\n\n副 词:  \nnoticeably"]}, {"dict": "adult self-study examination", "values": ["adj.值得注意的"]}, {"dict": "cet4", "values": ["显而易见的"]}, {"dict": "coca_20000", "values": ["adj.显而易见的，明显的,引人注目的，令人瞩目的,显著的，重要的,可以察觉的"]}, {"dict": "dancimimi_1", "values": ["adj. 显而易见的，显著的；值得注意的"]}, {"dict": "ielts", "values": ["显而易见的； 明显的"]}, {"dict": "ieltsWang11", "values": ["显著的"]}, {"dict": "ielts_disorder", "values": ["a. 显而易见的，值得注意的，重要的"]}, {"dict": "ielts_order", "values": ["a. 显而易见的，值得注意的，重要的"]}, {"dict": "level4", "values": ["显而易见的，显著的；值得注意的"]}, {"dict": "level8", "values": ["显而易见的，显著的；值得注意的"]}, {"dict": "pets3-2023", "values": ["adj.显而易见的，重要的"]}, {"dict": "sat", "values": ["显而易见的， 值得注意的"]}, {"dict": "toefl", "values": ["明显的， 值得注意的"]}, {"dict": "xinghuoqiaoji_4", "values": ["adj. 显而易见的，显著的；值得注意的"]}], "usphone": "ˈnoʊtɪsəbl", "ukphone": "ˈnəʊtɪsəbl"}