{"name": "spoken", "trans": [{"dict": "4000_Essential_English_Words1", "values": ["Spoken language is what we say."]}, {"dict": "4000_Essential_English_Words2", "values": ["We cannot take back what has been spoken."]}, {"dict": "Oxford5000", "values": ["adj. 口语的，口头的", "v. 说（speak的过去分词）"]}, {"dict": "Oxford5000", "values": ["adj. 口语的，口头的", "v. 说（speak的过去分词）"]}, {"dict": "coca_20000", "values": ["adj.口头讲的,口头的,口语的,（用以构成复合词）具…说话特点的v.讲，谈（ speak的过去分词 ）,说,演说,从某种观点来说"]}, {"dict": "dancimimi_1", "values": ["v. 说（speak的过去分词）", "adj. 口语的，口头的"]}, {"dict": "dancimimi_2", "values": ["v. 说（speak的过去分词）", "adj. 口语的，口头的"]}, {"dict": "level8", "values": ["口语的，口头的", "说（speak的过去分词）"]}], "usphone": "'spokən", "ukphone": "'spəʊk(ə)n"}