{"name": "stalwart", "trans": [{"dict": "GRE-computer-based-test", "values": ["adj. marked by outstanding strength and vigor of body, mind, or spirit", "健壮的", "adj. very loyal and dedicated 忠实的，坚定的"]}, {"dict": "ZaiYaoNiMing_GRE3000", "values": ["adj. 坚定的"]}, {"dict": "coca_20000", "values": ["adj.强壮的,结实的,坚定的,可靠的n.高大健壮的人,忠实拥护者"]}, {"dict": "gre", "values": ["健壮的； 坚定的"]}, {"dict": "gre3000", "values": ["坚定的"]}, {"dict": "level8", "values": ["坚定的；健壮的", "坚定分子"]}], "usphone": "ˈstɔ:lwərt", "ukphone": "ˈstɔ:lwət"}