{"name": "swirl", "trans": [{"dict": "coca_20000", "values": ["vi.旋转，打旋,眩晕,盘绕,大口喝酒vt.使成漩涡,使眼花,打转,弯曲盘旋n.（水，风等的）旋转，漩涡,<美>弯曲,涡状形,卷状的东西"]}, {"dict": "coca_20000", "values": ["vi.旋转，打旋,眩晕,盘绕,大口喝酒vt.使成漩涡,使眼花,打转,弯曲盘旋n.（水，风等的）旋转，漩涡,<美>弯曲,涡状形,卷状的东西"]}, {"dict": "gre", "values": ["旋转", "旋涡"]}, {"dict": "ielts_disorder", "values": ["n.漩涡, 涡状形。vt.使成漩涡。vi.打漩, 盘绕, 头晕。vi.<口>挥击, 大口喝酒"]}, {"dict": "ielts_order", "values": ["n.漩涡, 涡状形。vt.使成漩涡。vi.打漩, 盘绕, 头晕。vi.<口>挥击, 大口喝酒"]}, {"dict": "level8", "values": ["漩涡；打旋；涡状形", "盘绕；打旋；眩晕；大口喝酒"]}, {"dict": "toefl", "values": ["打旋， 旋转", "漩涡；螺旋形"]}], "usphone": "swɜ:rl", "ukphone": "swɜ:l"}