{"name": "paramount", "trans": [{"dict": "ZaiYaoNiMing_GRE3000", "values": ["adj.最重要的"]}, {"dict": "bec2", "values": ["最重要的，主要的；至高无上的", "最高统治者"]}, {"dict": "bec3", "values": ["极为重要的", "最高统治者"]}, {"dict": "coca_20000", "values": ["adj.最高的，至上的,最重要的，主要的,卓越的,有最高权力的n.最高，至上,有最高权力的人,元首，首长"]}, {"dict": "gmat", "values": ["最重要的， 决定性的"]}, {"dict": "gre", "values": ["最重要的； 最高权力的， 至高无上的"]}, {"dict": "gre3000", "values": ["最重要的"]}, {"dict": "ielts", "values": ["最重要的，决定性的", "最高统治者"]}, {"dict": "ielts-real-1", "values": ["adj. 最高的，至上的；首要的，主要的名 词: paramountcy"]}, {"dict": "ielts_disorder", "values": ["adj.极为重要的。"]}, {"dict": "ielts_order", "values": ["adj.极为重要的。"]}, {"dict": "level8", "values": ["最重要的，主要的；至高无上的", "最高统治者"]}, {"dict": "sat", "values": ["最重要的"]}, {"dict": "toefl", "values": ["至为重要的； 最高权力的， 至尊的"]}], "usphone": "'pærəmaʊnt", "ukphone": "'pærəmaʊnt"}