{"name": "pepper", "trans": [{"dict": "IELTSVocabularyBible", "values": ["n. 胡椒；辣椒；胡椒粉 vt. 加胡椒粉于；使布满"]}, {"dict": "Oxford5000", "values": ["n. 胡椒粉辣椒", "vt. 在…上撒胡椒粉；使布满以…密击，接二连三地提问", "时态:peppered，peppering，peppers"]}, {"dict": "Oxford5000", "values": ["n. 胡椒粉辣椒", "vt. 在…上撒胡椒粉；使布满以…密击，接二连三地提问", "时态:peppered，peppering，peppers"]}, {"dict": "PTE_Basic_apeuni", "values": ["n. 胡椒；辣椒；胡椒粉"]}, {"dict": "PTE_junior", "values": ["- n. 胡椒粉\n- 辣椒\n- vt. 在…上撒胡椒粉；使布满\n- 以…密击，接二连三地提问\n\n时 态:  \npeppered，peppering，peppers"]}, {"dict": "TOEFL_ZhangHongYan", "values": ["n. 胡椒粉；辣椒，甜椒，灯笼椒；胡椒；辣椒粉；（棒球）热身投击球练习 v. （在食物上）撒胡椒粉；连续射击；在……上撒，使布满； （演讲、文章等）充满……"]}, {"dict": "adult self-study examination", "values": ["n.胡椒"]}, {"dict": "cet4", "values": ["胡椒，胡椒粉", "在…上撒； 使布满"]}, {"dict": "coca_20000", "values": ["n.胡椒,辣椒,胡椒粉vt.在…上撒胡椒粉,使布满"]}, {"dict": "coca_20000", "values": ["n.胡椒,辣椒,胡椒粉vt.在…上撒胡椒粉,使布满"]}, {"dict": "heqiong", "values": ["辣椒；胡椒粉"]}, {"dict": "ielts", "values": ["胡椒", "在…上撒"]}, {"dict": "ielts_disorder", "values": ["n. 胡椒粉，胡椒；辣椒"]}, {"dict": "ielts_order", "values": ["n. 胡椒粉，胡椒；辣椒"]}, {"dict": "kaoyan", "values": ["胡椒粉， 胡椒；辣椒"]}, {"dict": "kaoyan_2024", "values": ["n.胡椒；辣椒；胡椒粉vt.加胡椒粉于；使布满"]}, {"dict": "level8", "values": ["胡椒；辣椒；胡椒粉", "加胡椒粉于；使布满"]}, {"dict": "longman_communication_3000_words", "values": ["胡椒, 辣椒, 胡椒粉, 花椒 (noun.)"]}, {"dict": "toefl", "values": ["胡椒；辣椒", "撒胡椒粉； 大量给予"]}, {"dict": "xinghuoqiaoji_6", "values": ["n. 胡椒；辣椒；胡椒粉,vt. 加胡椒粉于；使布满"]}], "usphone": "[ˈpepər]", "ukphone": "ˈpepə(r)"}