{"name": "plan", "trans": [{"dict": "4000_Essential_English_Words1", "values": ["To plan is to think about and arrange the details of something you want to do."]}, {"dict": "4000_Essential_English_Words2", "values": ["It’s Sam’s turn to plan the company party."]}, {"dict": "DuckCircle_IELTS", "values": ["n. 计划；平面图", "vt. 计划；设计；打算", "vi. 计划；打算"]}, {"dict": "English_II", "values": ["n.&vt.计划"]}, {"dict": "IELTS-807", "values": ["计划"]}, {"dict": "Oxford5000", "values": ["n. 平面图；计划", "vt. 计划；设计；打算", "vi. 计划；打算", "时态:planned, planning, plans名 词:planner"]}, {"dict": "Oxford5000", "values": ["n. 平面图；计划", "vt. 计划；设计；打算", "vi. 计划；打算", "时态:planned, planning, plans名 词:planner"]}, {"dict": "adult self-study examination", "values": ["n.计划"]}, {"dict": "bec2", "values": ["计划；平面图", "计划；设计；打算"]}, {"dict": "bec3", "values": ["计划， 给…制订计划", "计划，打算；方法；平面图，示意图，设计图"]}, {"dict": "coca_20000", "values": ["n.计划,打算,平面图,示意图vt.& vi.计划，打算，设计"]}, {"dict": "coca_20000", "values": ["n.计划,打算,平面图,示意图vt.& vi.计划，打算，设计"]}, {"dict": "dancimimi_1", "values": ["n. 计划；平面图", "vt. 计划；设计；打算", "vi. 计划；打算"]}, {"dict": "dancimimi_2", "values": ["n. 计划；平面图", "vt. 计划；设计；打算", "vi. 计划；打算"]}, {"dict": "ieltsWang3", "values": ["计划"]}, {"dict": "ielts_disorder", "values": ["n. 计划，规划；平面图，设计图v. 计划"]}, {"dict": "ielts_order", "values": ["n. 计划，规划；平面图，设计图v. 计划"]}, {"dict": "kaoyan_2024", "values": ["n. 计划；平面图vt. 计划；设计；打算vi. 计划；打算"]}, {"dict": "level4", "values": ["计划；平面图", "计划；设计；打算"]}, {"dict": "level8", "values": ["计划；平面图", "计划；设计；打算"]}, {"dict": "longman_communication_3000_words", "values": ["计划, 规划, 方案, 策划 (noun.)"]}, {"dict": "pets3", "values": ["v./n.计划，打算"]}, {"dict": "pets3-2023", "values": ["n.计划，策略，方法，vt.计划，设计，打算vi.打算"]}, {"dict": "self-study_English1", "values": ["n .计划，设计图，平面图；vt .计划，设计"]}, {"dict": "self-study_English2", "values": ["n. 计划；平面图"]}, {"dict": "self-study_English3", "values": ["n. 计划；平面图", "vt. 计划；设计；打算", "vi. 计划；打算"]}, {"dict": "self-study_English3", "values": ["n. 计划；平面图", "vt. 计划；设计；打算", "vi. 计划；打算"]}, {"dict": "top_1000_verb_Words", "values": ["To plan is to make arrangements or prepare for an event or goal that will happen in the future."]}, {"dict": "top_1500_nouns_Words", "values": ["A plan is a course of action or strategy designed to achieve a goal."]}, {"dict": "top_2000_English_Words", "values": ["noun, verb"]}, {"dict": "voa", "values": ["计划"]}, {"dict": "xinghuoqiaoji_6", "values": ["n. 计划；平面图,vt. 计划；设计；打算,vi. 计划；打算"]}], "usphone": "plæn", "ukphone": "plæn"}