{"name": "profile", "trans": [{"dict": "4000_Essential_English_Words1", "values": ["A profile is an outline of a face, usually as seen from the side."]}, {"dict": "4000_Essential_English_Words2", "values": ["The drawing of Olivia’s profile came out very well."]}, {"dict": "IELTS-807", "values": ["简介"]}, {"dict": "IELTSVocabularyBible", "values": ["n. 侧面；轮廓；外形；剖面；简况 vt. 描…的轮廓；扼要描述 vi. 给出轮廓"]}, {"dict": "IELTS_tinglichangjing", "values": ["轮廓"]}, {"dict": "IELTS_tinglichangjing", "values": ["外形"]}, {"dict": "PTE_Advanced_apeuni.json", "values": ["n. 侧面；轮廓；外形；剖面；简况"]}, {"dict": "PTE_Basic_apeuni", "values": ["n. 侧面；轮廓；外形；剖面；简况"]}, {"dict": "PTE_FIB_R_senior", "values": ["n. 侧面，轮廓，外形，剖面\n\n\n时 态:  \nprofiled, profiling, profiles \n\n名 词:  \nprofiler"]}, {"dict": "PTE_junior", "values": ["n. 侧面，轮廓，外形，剖面\n\n\n时 态:  \nprofiled, profiling, profiles \n\n名 词:  \nprofiler"]}, {"dict": "PTE_senior", "values": ["n. 侧面，轮廓，外形，剖面\n\n\n时 态:  \nprofiled, profiling, profiles \n\n名 词:  \nprofiler"]}, {"dict": "TOEFL_ZhangHongYan", "values": ["n. （人头部的）侧面（像），侧影；（某物的）外形，轮廓；（人、团体或组织的）简介，概况；（人或组织的）形象，姿态；纵断面，剖面；（地球表面纵断面的）轮廓（如河流走向）；（舞台的）平面布景；（以数量形式记录事物特点的）曲线图，数据图表；（记载个人心理或行为特点、喜好等的）档案 v. 概述，扼要介绍；给……画侧面像，显出……侧面轮廓；显出……的轮廓（be profiled）；（尤指用模板）铣出轮廓，使……成形"]}, {"dict": "TOEIC", "values": ["n. 侧面，轮廓，外形，剖面", "时态:profiled, profiling, profiles名 词:profiler"]}, {"dict": "adult self-study examination", "values": ["n.(面部的)侧影;简介"]}, {"dict": "bec2", "values": ["侧面；轮廓；外形；剖面；简况", "描…的轮廓；扼要描述"]}, {"dict": "bec3", "values": ["简介，人物简介；传略；形象，侧面，轮廓；姿态，引人注目的状态", "为…描绘； 写…的传略"]}, {"dict": "cet4", "values": ["侧面；人物简介；轮廓，形象；姿态，引人注目的状态", "为…描绘； 写…的传略"]}, {"dict": "cet6-sub", "values": ["n. 侧面；轮廓；外形；剖面；简况", "vt. 描…的轮廓；扼要描述", "vi. 给出轮廓"]}, {"dict": "cet6-sub", "values": ["n. 侧面；轮廓；外形；剖面；简况", "vt. 描…的轮廓；扼要描述", "vi. 给出轮廓"]}, {"dict": "coca_20000", "values": ["n.侧面，半面,外形，轮廓,航翼型,人物简介vt.描…的轮廓,给…画侧面图,为（某人）写传略,机铣出…的轮廓"]}, {"dict": "coca_20000", "values": ["n.侧面，半面,外形，轮廓,航翼型,人物简介vt.描…的轮廓,给…画侧面图,为（某人）写传略,机铣出…的轮廓"]}, {"dict": "dancimimi_1", "values": ["n. 侧面；轮廓；外形；剖面；简况", "vt. 描…的轮廓；扼要描述", "vi. 给出轮廓"]}, {"dict": "dancimimi_2", "values": ["n. 侧面；轮廓；外形；剖面；简况", "vt. 描…的轮廓；扼要描述", "vi. 给出轮廓"]}, {"dict": "gmat", "values": ["剖面； 轮廓； 分布图"]}, {"dict": "gre", "values": ["轮廓， 外形； 侧面"]}, {"dict": "ielts", "values": ["面部的侧影，侧面轮廓；传略，人物简介", "扼要介绍； 写传略"]}, {"dict": "ieltsWang11", "values": ["个人简介"]}, {"dict": "ielts_disorder", "values": ["n. 侧面;轮廓"]}, {"dict": "ielts_order", "values": ["n. 侧面;轮廓"]}, {"dict": "itVocabulary", "values": ["n.简要，剖面，概貌"]}, {"dict": "kaoyan", "values": ["侧面；轮廓， 外形；人物简介"]}, {"dict": "kaoyan_2024", "values": ["n.侧面；轮廓；外形；剖面；简况vt.描…的轮廓；扼要描述vi.给出轮廓"]}, {"dict": "kaoyanshanguo_2023", "values": ["n. 侧影；人物简介；轮廓vt. 概述"]}, {"dict": "level4", "values": ["侧面；轮廓；外形；剖面；简况", "描…的轮廓；扼要描述"]}, {"dict": "level8", "values": ["侧面；轮廓；外形；剖面；简况", "描…的轮廓；扼要描述"]}, {"dict": "longman_communication_3000_words", "values": ["配置文件, 剖面, 概要文件, 轮廓 (noun.)"]}, {"dict": "sat", "values": ["侧面 ； 轮廓， 外形； 人物简介"]}, {"dict": "toefl", "values": ["人物专访；概述，传略，人物简介；面部的侧影；轮廓，外形", "扼要介绍， 概述"]}, {"dict": "top_1000_verb_Words", "values": ["To profile is to create a detailed description or analysis of a person, organization, or thing, often for investigative or marketing purposes."]}, {"dict": "top_1500_nouns_Words", "values": ["A profile is a description or summary of someone or something, often focusing on their characteristics or features."]}, {"dict": "top_2000_English_Words", "values": ["noun, verb"]}, {"dict": "xinghuoqiaoji_4", "values": ["n. 侧面；轮廓；外形；剖面；简况,vt. 描…的轮廓；扼要描述,vi. 给出轮廓"]}, {"dict": "xinghuoqiaoji_6", "values": ["n. 侧面；轮廓；外形；剖面；简况,vt. 描…的轮廓；扼要描述,vi. 给出轮廓"]}], "usphone": "'profaɪl", "ukphone": "'proufaɪl"}