{"name": "yield", "trans": [{"dict": "2024HongBao T2", "values": ["生产，产生，带来；放弃，屈服；产量，收获"]}, {"dict": "4000_Essential_English_Words1", "values": ["To yield something means to give up control of it or to give it away."]}, {"dict": "4000_Essential_English_Words2", "values": ["He had to yield his turn because he was in checkmate."]}, {"dict": "GRE-computer-based-test", "values": ["v. to produce or provide 产生", "v. to surrender or submit to another 屈服"]}, {"dict": "GRE_equivalent", "values": ["succumb, engender, output"]}, {"dict": "IELTSVocabularyBible", "values": ["n. 产量；收益 vt. 屈服；出产，产生；放弃 vi. 屈服，投降"]}, {"dict": "Oxford5000", "values": ["vt. 出产；屈服；放弃", "vi. 屈服，投降", "n. 收益；产量", "时态:yielded, yielding, yields名 词:yielder"]}, {"dict": "Oxford5000", "values": ["vt. 出产；屈服；放弃", "vi. 屈服，投降", "n. 收益；产量", "时态:yielded, yielding, yields名 词:yielder"]}, {"dict": "PTE_Basic_apeuni", "values": ["n. 产量；收益"]}, {"dict": "PTE_FIB_R_junior", "values": ["- vt. 出产；屈服；放弃\n- vi. 屈服，投降\n- n. 收益；产量\n\n\n时 态:  \nyielded, yielding, yields \n\n名 词:  \nyielder"]}, {"dict": "PTE_junior", "values": ["- vt. 出产；屈服；放弃\n- vi. 屈服，投降\n- n. 收益；产量\n\n\n时 态:  \nyielded, yielding, yields \n\n名 词:  \nyielder"]}, {"dict": "TOEIC", "values": ["vt. 出产；屈服；放弃", "vi. 屈服，投降", "n. 收益；产量", "时态:yielded, yielding, yields名 词:yielder"]}, {"dict": "adult self-study examination", "values": ["v.屈服;产生"]}, {"dict": "bec2", "values": ["屈服；出产，产生；放弃", "产量；收益"]}, {"dict": "bec3", "values": ["屈服，顺从；倒塌，垮掉；产出，产生；让渡，让与", "产量， 产额； 收益， 利润"]}, {"dict": "cet4", "values": ["出产；让出，放弃；屈服，顺从；倒塌，垮掉", "产量"]}, {"dict": "cet4-sub", "values": ["n. 产量；收益", "vt. 屈服；出产，产生；放弃", "vi. 屈服，投降"]}, {"dict": "cet6", "values": ["出产；让出，放弃；屈服，顺从；倒塌，垮掉 (v.)", "产量 (n.)"]}, {"dict": "coca_20000", "values": ["vt.屈服，投降,生产,获利,不再反对vi.放弃，屈服,生利,退让，退位n.产量，产额,投资的收益,屈服，击穿,产品"]}, {"dict": "coca_20000", "values": ["vt.屈服，投降,生产,获利,不再反对vi.放弃，屈服,生利,退让，退位n.产量，产额,投资的收益,屈服，击穿,产品"]}, {"dict": "dancimimi_1", "values": ["n. 产量；收益", "vt. 屈服；出产，产生；放弃", "vi. 屈服，投降"]}, {"dict": "dancimimi_2", "values": ["n. 产量；收益", "vt. 屈服；出产，产生；放弃", "vi. 屈服，投降"]}, {"dict": "gmat", "values": ["产生； 屈从", "产量；"]}, {"dict": "heqiong", "values": ["屈服；生产；生产量"]}, {"dict": "ielts", "values": ["出产； 放弃", "产量"]}, {"dict": "ielts-real-high", "values": ["vt. 出产；屈服；放弃; vi. 屈服，投降; n. 收益；产量 时 态: yielded, yielding, yields 名 词: yielder"]}, {"dict": "ielts_disorder", "values": ["vt./vi. 生产;生长;让步;投降;屈服;n. 产量"]}, {"dict": "ielts_order", "values": ["vt./vi. 生产;生长;让步;投降;屈服;n. 产量"]}, {"dict": "kaoyan", "values": ["屈服， 服从", "出产， 生长", "产量， 收获"]}, {"dict": "kaoyan_2024", "values": ["n. 产量；收益vt. 屈服；出产，产生；放弃vi. 屈服，投降"]}, {"dict": "kaoyanshanguo_2023", "values": ["vi. 屈服vt. 缴出；产出n. 产量"]}, {"dict": "level4", "values": ["屈服；出产，产生；放弃", "产量；收益"]}, {"dict": "level8", "values": ["屈服；出产，产生；放弃", "产量；收益"]}, {"dict": "pets3", "values": ["v.生产；(to)屈服，服从 n.产量，收成"]}, {"dict": "pets3-2023", "values": ["vt.，&，vi.出产，屈服，投降，弯下去，凹下去，n.产量，生产量，投资收益"]}, {"dict": "toefl", "values": ["生产，出产；屈服，顺从；让出，放弃；变形，弯曲", "产量； 收益"]}, {"dict": "xinghuoqiaoji_6", "values": ["n. 产量；收益,vt. 屈服；出产，产生；放弃,vi. 屈服，投降"]}], "usphone": "jiːld", "ukphone": "jiːld"}