{"name": "humanity", "trans": [{"dict": "2024HongBao T2", "values": ["人类；人性；人文科学"]}, {"dict": "English_II", "values": ["n.个性，博爱，仁慈；人类"]}, {"dict": "Oxford5000", "values": ["n. 人类；人道；仁慈；人文学科"]}, {"dict": "Oxford5000", "values": ["n. 人类；人道；仁慈；人文学科"]}, {"dict": "PTE_Advanced_apeuni.json", "values": ["n. 人类；人道；仁慈；人文学科"]}, {"dict": "PTE_Basic_apeuni", "values": ["n. 人类；人道；仁慈；人文学科"]}, {"dict": "PTE_FIB_L", "values": ["n. 人类；人道；仁慈；人文学科"]}, {"dict": "PTE_FIB_R_senior", "values": ["n. 人类；人道；仁慈；人文学科"]}, {"dict": "PTE_junior", "values": ["n. 人类；人道；仁慈；人文学科"]}, {"dict": "PTE_senior", "values": ["n. 人类；人道；仁慈；人文学科"]}, {"dict": "cet4-sub", "values": ["n. 人类；人道；仁慈；人文学科"]}, {"dict": "cet6", "values": ["人类， 人； 人性； 人道， 博爱； 人文学科 (n.)"]}, {"dict": "coca_20000", "values": ["n.人类,人性,人道,人文学科"]}, {"dict": "dancimimi_1", "values": ["n. 人类；人道；仁慈；人文学科"]}, {"dict": "ielts", "values": ["人类，人；人性；人道，仁慈；"]}, {"dict": "ielts-real-4", "values": ["n. 人类；人道；仁慈；人文学科"]}, {"dict": "ielts_disorder", "values": ["n. 人类,仁慈,仁爱"]}, {"dict": "ielts_order", "values": ["n. 人类,仁慈,仁爱"]}, {"dict": "kaoyan", "values": ["人类； 人性， 人情；人文科学 A"]}, {"dict": "kaoyan_2024", "values": ["n. 人类；人道；仁慈；人文学科"]}, {"dict": "level8", "values": ["人类；人道；仁慈；人文学科"]}, {"dict": "sat", "values": ["人类， 人性， 人情； 人文科学"]}, {"dict": "self-study_English3", "values": ["n. 人类；人道；仁慈；人文学科"]}, {"dict": "toefl", "values": ["人类； 人性； 人道， 仁慈"]}, {"dict": "xinghuoqiaoji_4", "values": ["n. 人类；人道；仁慈；人文学科"]}, {"dict": "xinghuoqiaoji_6", "values": ["n. 人类；人道；仁慈；人文学科"]}, {"dict": "xinghuoqiaoji_6", "values": ["n. 人类；人道；仁慈；人文学科"]}], "usphone": "hjuːˈmænəti", "ukphone": "hjuːˈmænəti"}