{"name": "multimedia", "trans": [{"dict": "English_II", "values": ["a.多种手段的；多媒体的", "n.多媒体"]}, {"dict": "IELTSVocabularyBible", "values": ["n. 多媒体 adj. 多媒体的"]}, {"dict": "PTE_Advanced_apeuni.json", "values": ["n. 多媒体"]}, {"dict": "PTE_senior", "values": ["n. 多媒体"]}, {"dict": "TOEIC", "values": ["n. 多媒体"]}, {"dict": "coca_20000", "values": ["n.多媒体adj.多媒体的"]}, {"dict": "heqiong", "values": ["多媒体"]}, {"dict": "level8", "values": ["多媒体", "多媒体的"]}, {"dict": "self-study_English3", "values": ["n. 多媒体", "adj. 多媒体的"]}], "usphone": ",mʌltɪ'midɪə", "ukphone": "'mʌltɪmiːdɪə"}