{"name": "keen", "trans": [{"dict": "4000_Essential_English_Words1", "values": ["If someone is keen, they are intelligent."]}, {"dict": "4000_Essential_English_Words2", "values": ["Only a keen student could have solved that math problem."]}, {"dict": "GRE-computer-based-test", "values": ["adj. very excited about and interested in something 渴望的"]}, {"dict": "GRE_equivalent", "values": ["eager"]}, {"dict": "IELTSVocabularyBible", "values": ["adj. 敏锐的，敏捷的；渴望的；强烈的；热心的；锐利的 n. 痛哭，挽歌"]}, {"dict": "Oxford5000", "values": ["adj. 锋利的热衷的，热心的，渴望(做某事)激烈的，紧张的良好的；敏锐的，敏捷的比较级:keener，keenest副 词:keenly", "名 词:keenness", "名 词:keener"]}, {"dict": "Oxford5000", "values": ["adj. 锋利的热衷的，热心的，渴望(做某事)激烈的，紧张的良好的；敏锐的，敏捷的比较级:keener，keenest副 词:keenly", "名 词:keenness", "名 词:keener"]}, {"dict": "PTE_Advanced_apeuni.json", "values": ["adj. 敏锐的，敏捷的；渴望的；强烈的；热心的；锐利的"]}, {"dict": "PTE_Basic_apeuni", "values": ["adj. 敏锐的，敏捷的；渴望的；强烈的；热心的；锐利的"]}, {"dict": "PTE_junior", "values": ["- adj. 锋利的\n- 热衷的，热心的，渴望(做某事)\n- 激烈的，紧张的\n- 良好的；敏锐的，敏捷的\n\n比较级:  \nkeener，keenest \n\n副 词:  \nkeenly\n\n名 词:  \nkeenness\n\n名 词:  \nkeener"]}, {"dict": "PTE_senior", "values": ["- adj. 锋利的\n- 热衷的，热心的，渴望(做某事)\n- 激烈的，紧张的\n- 良好的；敏锐的，敏捷的\n\n比较级:  \nkeener，keenest \n\n副 词:  \nkeenly\n\n名 词:  \nkeenness\n\n名 词:  \nkeener"]}, {"dict": "TOEIC", "values": ["adj. 锋利的热衷的，热心的，渴望(做某事)激烈的，紧张的良好的；敏锐的，敏捷的比较级:keener，keenest副 词:keenly", "名 词:keenness", "名 词:keener"]}, {"dict": "adult self-study examination", "values": ["adj.敏锐的"]}, {"dict": "bec2", "values": ["敏锐的，敏捷的；渴望的；强烈的；热心的；锐利的", "痛哭，挽歌"]}, {"dict": "bec3", "values": ["渴望的； 热心的； 精明的； 敏锐的， 敏捷的； 激烈的， 强烈的； 锋利的； 刺人的"]}, {"dict": "cet4", "values": ["热心的； 激烈的； 敏锐的， 敏捷的"]}, {"dict": "cet4-sub", "values": ["adj. 敏锐的，敏捷的；渴望的；强烈的；热心的；锐利的", "n. 痛哭，挽歌"]}, {"dict": "cet6", "values": ["热心的； 激烈的； 敏锐的， 敏捷的 (adj.)"]}, {"dict": "cet6-sub", "values": ["adj. 敏锐的，敏捷的；渴望的；强烈的；热心的；锐利的", "n. 痛哭，挽歌"]}, {"dict": "coca_20000", "values": ["adj.厉害的，强烈的,敏锐的，敏捷的,锐利的,热心的vi.（为死者）恸哭，哀号n.〈英〉号哭，恸哭"]}, {"dict": "dancimimi_1", "values": ["adj. 敏锐的，敏捷的；渴望的；强烈的；热心的；锐利的", "n. 痛哭，挽歌"]}, {"dict": "dancimimi_2", "values": ["adj. 敏锐的，敏捷的；渴望的；强烈的；热心的；锐利的", "n. 痛哭，挽歌"]}, {"dict": "dancimimi_2", "values": ["adj. 敏锐的，敏捷的；渴望的；强烈的；热心的；锐利的", "n. 痛哭，挽歌"]}, {"dict": "gre", "values": ["锋利的， 锐利的； 敏锐的， 灵敏的； 热心的"]}, {"dict": "heqiong", "values": ["敏锐的；强烈的；热衷的"]}, {"dict": "ielts", "values": ["热衷的， 热心的， 渴望的； 敏锐的， 敏捷的； 激烈的， 紧张的； 锋利的"]}, {"dict": "ielts-real-high", "values": ["adj. 锋利的; 热衷的，热心的，渴望; 激烈的，紧张的; 良好的；敏锐的，敏捷的 比较级: keener，keenest 副 词: keenly 名 词: kee..."]}, {"dict": "ielts_disorder", "values": ["a. 锋利的,尖锐的,强烈的;敏锐的;渴望的"]}, {"dict": "ielts_order", "values": ["a. 锋利的,尖锐的,强烈的;敏锐的;渴望的"]}, {"dict": "kaoyan", "values": ["热心的， 渴望的；敏锐的； 头脑敏捷的；锋利的"]}, {"dict": "level4", "values": ["敏锐的，敏捷的；渴望的；强烈的；热心的；锐利的", "痛哭，挽歌"]}, {"dict": "level8", "values": ["敏锐的，敏捷的；渴望的；强烈的；热心的；锐利的", "痛哭，挽歌"]}, {"dict": "longman_communication_3000_words", "values": ["敏锐, 热衷于, 热衷, 浓厚 (adj.)"]}, {"dict": "pets3-2023", "values": ["adj.热心的，激烈的，敏锐的，强烈的，精明的，热忠于"]}, {"dict": "toefl", "values": ["灵敏的， 敏锐的； 热心的， 渴望的； 激烈的； 锋利的"]}, {"dict": "xinghuoqiaoji_4", "values": ["adj. 敏锐的，敏捷的；渴望的；强烈的；热心的；锐利的,n. 痛哭，挽歌"]}, {"dict": "xinghuoqiaoji_6", "values": ["adj. 敏锐的，敏捷的；渴望的；强烈的；热心的；锐利的,n. 痛哭，挽歌"]}], "usphone": "kin", "ukphone": "kiːn"}