{"name": "tackle", "trans": [{"dict": "4000_Essential_English_Words1", "values": ["To tackle something means to deal with it in a determined and efficient way."]}, {"dict": "4000_Essential_English_Words2", "values": ["Such social problems need to be tackled right away."]}, {"dict": "DuckCircle_IELTS", "values": ["n. 滑车；装备；用具；扭倒", "vi. 扭倒；拦截抢球", "vt. 处理；抓住；固定；与…交涉"]}, {"dict": "IELTSVocabularyBible", "values": ["n. 滑车；装备；用具；扭倒 vi. 扭倒；拦截抢球 vt. 处理；抓住；固定；与…交涉"]}, {"dict": "Oxford5000", "values": ["vt. 解决；应付", "vt. & vi. 捉住；扭倒", "n. 拦截；擒抱器具，器械，用具滑车，滑轮组", "时态:tackled，tackling，tackles名 词:tackler"]}, {"dict": "Oxford5000", "values": ["vt. 解决；应付", "vt. & vi. 捉住；扭倒", "n. 拦截；擒抱器具，器械，用具滑车，滑轮组", "时态:tackled，tackling，tackles名 词:tackler"]}, {"dict": "Oxford5000", "values": ["vt. 解决；应付", "vt. & vi. 捉住；扭倒", "n. 拦截；擒抱器具，器械，用具滑车，滑轮组", "时态:tackled，tackling，tackles名 词:tackler"]}, {"dict": "Oxford5000", "values": ["vt. 解决；应付", "vt. & vi. 捉住；扭倒", "n. 拦截；擒抱器具，器械，用具滑车，滑轮组", "时态:tackled，tackling，tackles名 词:tackler"]}, {"dict": "PTE_Basic_apeuni", "values": ["n. 滑车；装备；用具；扭倒"]}, {"dict": "PTE_junior", "values": ["- vt. 解决；应付\n- vt. & vi. 捉住；扭倒\n- n. 拦截；擒抱\n- 器具，器械，用具\n- 滑车，滑轮组\n\n时 态:  \ntackled，tackling，tackles \n\n名 词:  \ntackler"]}, {"dict": "TOEFL_ZhangHongYan", "values": ["v. 应付，解决（难题或局面）；与……交涉；（足球、曲棍球等比赛中）抢断；（橄榄球等比赛中）擒抱并摔倒（对方球员）；擒获；对付，打（尤指罪犯）；质问，责问；反对，反抗 n. （足球等中的）抢断球；（橄榄球或美式足球）擒抱摔倒；（美式足球中的）阻截队员；体育器械，（尤指）渔具；（吊起重物用的）索具，滑轮；&lt;英，俚&gt;男性性器官"]}, {"dict": "ZaiYaoNiMing_GRE3000", "values": ["vt. 着手处理"]}, {"dict": "bec2", "values": ["滑车；装备；用具；扭倒", "处理；抓住；固定；与…交涉"]}, {"dict": "bec3", "values": ["对付，处理；与…交涉；阻截，擒抱", "阻截， 擒抱； 用具， 钓具； 辘轳， 滑车"]}, {"dict": "cet4", "values": ["对付，处理；与…交涉；阻截，擒抱", "阻截， 擒抱； 用具， 钓具； 辘轳， 滑车"]}, {"dict": "cet4-sub", "values": ["n. 滑车；装备；用具；扭倒", "vi. 扭倒；拦截抢球", "vt. 处理；抓住；固定；与…交涉"]}, {"dict": "cet6", "values": ["对付，处理；与…交涉；阻截，擒抱 (vt.)", "阻截， 擒抱； 用具， 钓具； 辘轳， 滑车 (n.)"]}, {"dict": "cet6-sub", "values": ["n. 滑车；装备；用具；扭倒", "vi. 扭倒；拦截抢球", "vt. 处理；抓住；固定；与…交涉"]}, {"dict": "coca_20000", "values": ["n.用具，装备,索具,阻挡,阻截队员vt.着手处理,橄榄球擒住并摔倒（一名对方球员）,给（马）配上挽具vi.擒住并摔倒一名对手"]}, {"dict": "coca_20000", "values": ["n.用具，装备,索具,阻挡,阻截队员vt.着手处理,橄榄球擒住并摔倒（一名对方球员）,给（马）配上挽具vi.擒住并摔倒一名对手"]}, {"dict": "dancimimi_1", "values": ["n. 滑车；装备；用具；扭倒", "vi. 扭倒；拦截抢球", "vt. 处理；抓住；固定；与…交涉"]}, {"dict": "dancimimi_1", "values": ["n. 滑车；装备；用具；扭倒", "vi. 扭倒；拦截抢球", "vt. 处理；抓住；固定；与…交涉"]}, {"dict": "gre", "values": ["处理", "滑车"]}, {"dict": "gre3000", "values": ["着手处理"]}, {"dict": "heqiong", "values": ["处理；对付"]}, {"dict": "ielts", "values": ["对付，处理；向某人提起；抢截，抢球", "用具， 器具； 滑轮， 滑车； 抢截"]}, {"dict": "ielts-real-5", "values": ["vt. 解决；应付; vt. & vi. 捉住；扭倒; n. 拦截；擒抱; 器具，器械，用具; 滑车，滑轮组 时 态: tackled，tackling，tackles 名 词:..."]}, {"dict": "ielts_disorder", "values": ["vt./vi. 处理,对付;抓住"]}, {"dict": "ielts_order", "values": ["vt./vi. 处理,对付;抓住"]}, {"dict": "kaoyan", "values": ["用具， 器械； 滑车", "处理， 解决， 对付 <"]}, {"dict": "kaoyan_2024", "values": ["n. 滑车；装备；用具；扭倒vi. 扭倒；拦截抢球vt. 处理；抓住；固定；与…交涉"]}, {"dict": "kaoyanshanguo_2023", "values": ["vt. 处理，解决；与......交涉；抓获"]}, {"dict": "level4", "values": ["滑车；装备；用具；扭倒", "处理；抓住；固定；与…交涉"]}, {"dict": "level8", "values": ["滑车；装备；用具；扭倒", "处理；抓住；固定；与…交涉"]}, {"dict": "longman_communication_3000_words", "values": ["解决, 对付, 应对, 应付 (verb.); 铲球, 钓具 (noun.)"]}, {"dict": "toefl", "values": ["对付，处理；阻截；抢球", "拦截； 用具"]}, {"dict": "top_1000_verb_Words", "values": ["To tackle is to confront or deal with a problem or challenge, or to physically grab and bring down an opponent in sports."]}, {"dict": "top_1500_nouns_Words", "values": ["To tackle is to confront or deal with a difficult problem or task."]}, {"dict": "top_2000_English_Words", "values": ["noun, verb"]}, {"dict": "xinghuoqiaoji_4", "values": ["n. 滑车；装备；用具；扭倒,vi. 扭倒；拦截抢球,vt. 处理；抓住；固定；与…交涉"]}, {"dict": "xinghuoqiaoji_6", "values": ["n. 滑车；装备；用具；扭倒,vi. 扭倒；拦截抢球,vt. 处理；抓住；固定；与…交涉"]}, {"dict": "xinghuoqiaoji_6", "values": ["n. 滑车；装备；用具；扭倒,vi. 扭倒；拦截抢球,vt. 处理；抓住；固定；与…交涉"]}], "usphone": "'tækl", "ukphone": "'tækl"}